<Properties StartupConfiguration="{5ECF50E6-77B6-412D-A853-B1CAAC51762F}|Default">
  <MonoDevelop.Ide.Workspace ActiveConfiguration="Debug" />
  <MonoDevelop.Ide.Workbench ActiveDocument="Midterm_Sample/Enor.cs">
    <Files>
      <File FileName="Midterm_Sample/Program.cs" Line="1" Column="1" />
      <File FileName="Midterm_Sample/Enor.cs" Line="20" Column="2" />
    </Files>
    <Pads>
      <Pad Id="ProjectPad">
        <State name="__root__">
          <Node name="Midterm_Sample" expanded="True">
            <Node name="Midterm_Sample" expanded="True">
              <Node name="Enor.cs" selected="True" />
            </Node>
          </Node>
        </State>
      </Pad>
    </Pads>
  </MonoDevelop.Ide.Workbench>
  <MultiItemStartupConfigurations />
  <MonoDevelop.Ide.ItemProperties.Midterm__Sample PreferredExecutionTarget="MonoDevelop.Default" FirstBuild="True" />
  <MonoDevelop.Ide.DebuggingService.Breakpoints>
    <BreakpointStore />
  </MonoDevelop.Ide.DebuggingService.Breakpoints>
  <MonoDevelop.Ide.DebuggingService.PinnedWatches />
</Properties>